sonounolib/__init__.py
sonounolib/extern/__init__.py
sonounolib/extern/wavfile.py
sonounolib/notes.py
sonounolib/players.py
sonounolib/py.typed
sonounolib/tracks.py
sonounolib/utils.py
sonounolib-0.5.3.dist-info/WHEEL
sonounolib-0.5.3.dist-info/METADATA
sonounolib-0.5.3.dist-info/RECORD
