Metadata-Version: 2.1
Name: sonounolib
Version: 0.5.3
Summary: Library of generic sonification components.
Author: Pierre Chanial
Author-email: pierre.chanial@apc.in2p3.fr
Requires-Python: >=3.8,<4.0
Classifier: Programming Language :: Python :: 3
Classifier: Programming Language :: Python :: 3.10
Classifier: Programming Language :: Python :: 3.8
Classifier: Programming Language :: Python :: 3.9
Requires-Dist: numpy (>=1.22.3,<2.0.0)
Requires-Dist: requests (>=2.27.1,<3.0.0)
Requires-Dist: sounddevice (>=0.4.4,<0.5.0)
Requires-Dist: streamunolib (>=0.4.3,<0.5.0)
